CHANGELOG.txt
LICENSE.txt
MANIFEST.in
README.md
setup.py
echo_uwu.egg-info/PKG-INFO
echo_uwu.egg-info/SOURCES.txt
echo_uwu.egg-info/dependency_links.txt
echo_uwu.egg-info/top_level.txt
venv/bin/rst2html.py
venv/bin/rst2html4.py
venv/bin/rst2html5.py
venv/bin/rst2latex.py
venv/bin/rst2man.py
venv/bin/rst2odt.py
venv/bin/rst2odt_prepstyles.py
venv/bin/rst2pseudoxml.py
venv/bin/rst2s5.py
venv/bin/rst2xetex.py
venv/bin/rst2xml.py
venv/bin/rstpep2html.py
venv/lib/python3.7/site-packages/pyparsing.py
venv/lib/python3.7/site-packages/six.py
venv/lib/python3.7/site-packages/typing_extensions.py
venv/lib/python3.7/site-packages/zipp.py
venv/lib/python3.7/site-packages/Pygments-2.9.0.dist-info/entry_points.txt
venv/lib/python3.7/site-packages/Pygments-2.9.0.dist-info/top_level.txt
venv/lib/python3.7/site-packages/SecretStorage-3.3.1.dist-info/top_level.txt
venv/lib/python3.7/site-packages/_distutils_hack/__init__.py
venv/lib/python3.7/site-packages/_distutils_hack/override.py
venv/lib/python3.7/site-packages/bleach/__init__.py
venv/lib/python3.7/site-packages/bleach/callbacks.py
venv/lib/python3.7/site-packages/bleach/html5lib_shim.py
venv/lib/python3.7/site-packages/bleach/linkifier.py
venv/lib/python3.7/site-packages/bleach/sanitizer.py
venv/lib/python3.7/site-packages/bleach/utils.py
venv/lib/python3.7/site-packages/bleach-3.3.0.dist-info/top_level.txt
venv/lib/python3.7/site-packages/bleach/_vendor/__init__.py
venv/lib/python3.7/site-packages/bleach/_vendor/vendor.txt
venv/lib/python3.7/site-packages/bleach/_vendor/Django-1.11.29.dist-info/entry_points.txt
venv/lib/python3.7/site-packages/bleach/_vendor/Django-1.11.29.dist-info/top_level.txt
venv/lib/python3.7/site-packages/bleach/_vendor/django/__init__.py
venv/lib/python3.7/site-packages/bleach/_vendor/django/core/__init__.py
venv/lib/python3.7/site-packages/bleach/_vendor/django/core/validators.py
venv/lib/python3.7/site-packages/bleach/_vendor/html5lib/__init__.py
venv/lib/python3.7/site-packages/bleach/_vendor/html5lib/_ihatexml.py
venv/lib/python3.7/site-packages/bleach/_vendor/html5lib/_inputstream.py
venv/lib/python3.7/site-packages/bleach/_vendor/html5lib/_tokenizer.py
venv/lib/python3.7/site-packages/bleach/_vendor/html5lib/_utils.py
venv/lib/python3.7/site-packages/bleach/_vendor/html5lib/constants.py
venv/lib/python3.7/site-packages/bleach/_vendor/html5lib/html5parser.py
venv/lib/python3.7/site-packages/bleach/_vendor/html5lib/serializer.py
venv/lib/python3.7/site-packages/bleach/_vendor/html5lib-1.1.dist-info/top_level.txt
venv/lib/python3.7/site-packages/bleach/_vendor/html5lib/_trie/__init__.py
venv/lib/python3.7/site-packages/bleach/_vendor/html5lib/_trie/_base.py
venv/lib/python3.7/site-packages/certifi-2020.12.5.dist-info/top_level.txt
venv/lib/python3.7/site-packages/cffi-1.14.5.dist-info/entry_points.txt
venv/lib/python3.7/site-packages/cffi-1.14.5.dist-info/top_level.txt
venv/lib/python3.7/site-packages/chardet-4.0.0.dist-info/entry_points.txt
venv/lib/python3.7/site-packages/chardet-4.0.0.dist-info/top_level.txt
venv/lib/python3.7/site-packages/colorama-0.4.4.dist-info/LICENSE.txt
venv/lib/python3.7/site-packages/colorama-0.4.4.dist-info/top_level.txt
venv/lib/python3.7/site-packages/cryptography-3.4.7.dist-info/top_level.txt
venv/lib/python3.7/site-packages/docutils-0.17.1.dist-info/COPYING.txt
venv/lib/python3.7/site-packages/docutils-0.17.1.dist-info/top_level.txt
venv/lib/python3.7/site-packages/idna-2.10.dist-info/top_level.txt
venv/lib/python3.7/site-packages/importlib_metadata-4.0.1.dist-info/top_level.txt
venv/lib/python3.7/site-packages/keyring-23.0.1.dist-info/entry_points.txt
venv/lib/python3.7/site-packages/keyring-23.0.1.dist-info/top_level.txt
venv/lib/python3.7/site-packages/packaging-20.9.dist-info/top_level.txt
venv/lib/python3.7/site-packages/pip-21.1.1.dist-info/LICENSE.txt
venv/lib/python3.7/site-packages/pip-21.1.1.dist-info/entry_points.txt
venv/lib/python3.7/site-packages/pip-21.1.1.dist-info/top_level.txt
venv/lib/python3.7/site-packages/pkginfo-1.7.0.dist-info/LICENSE.txt
venv/lib/python3.7/site-packages/pkginfo-1.7.0.dist-info/entry_points.txt
venv/lib/python3.7/site-packages/pkginfo-1.7.0.dist-info/top_level.txt
venv/lib/python3.7/site-packages/pycparser-2.20.dist-info/top_level.txt
venv/lib/python3.7/site-packages/pyparsing-2.4.7.dist-info/top_level.txt
venv/lib/python3.7/site-packages/readme_renderer-29.0.dist-info/entry_points.txt
venv/lib/python3.7/site-packages/readme_renderer-29.0.dist-info/top_level.txt
venv/lib/python3.7/site-packages/requests-2.25.1.dist-info/top_level.txt
venv/lib/python3.7/site-packages/requests_toolbelt-0.9.1.dist-info/top_level.txt
venv/lib/python3.7/site-packages/rfc3986-1.5.0.dist-info/top_level.txt
venv/lib/python3.7/site-packages/setuptools-56.2.0.dist-info/dependency_links.txt
venv/lib/python3.7/site-packages/setuptools-56.2.0.dist-info/entry_points.txt
venv/lib/python3.7/site-packages/setuptools-56.2.0.dist-info/top_level.txt
venv/lib/python3.7/site-packages/six-1.16.0.dist-info/top_level.txt
venv/lib/python3.7/site-packages/tqdm-4.60.0.dist-info/entry_points.txt
venv/lib/python3.7/site-packages/tqdm-4.60.0.dist-info/top_level.txt
venv/lib/python3.7/site-packages/twine-3.4.1.dist-info/entry_points.txt
venv/lib/python3.7/site-packages/twine-3.4.1.dist-info/top_level.txt
venv/lib/python3.7/site-packages/typing_extensions-3.10.0.0.dist-info/top_level.txt
venv/lib/python3.7/site-packages/urllib3-1.26.4.dist-info/LICENSE.txt
venv/lib/python3.7/site-packages/urllib3-1.26.4.dist-info/top_level.txt
venv/lib/python3.7/site-packages/webencodings-0.5.1.dist-info/top_level.txt
venv/lib/python3.7/site-packages/zipp-3.4.1.dist-info/top_level.txt
venv/lib64/python3.7/site-packages/Pygments-2.9.0.dist-info/entry_points.txt
venv/lib64/python3.7/site-packages/Pygments-2.9.0.dist-info/top_level.txt
venv/lib64/python3.7/site-packages/SecretStorage-3.3.1.dist-info/top_level.txt
venv/lib64/python3.7/site-packages/bleach-3.3.0.dist-info/top_level.txt
